awstools/__init__.py
awstools/accounts.py
awstools/aws_config.py
awstools/awscli_wrapper.py
awstools/awstools.py
awstools/awstools_show.py
awstools/ec2.py
awstools/ec2client.py
awstools/extract.py
awstools/get_accounts.py
awstools/iam.py
awstools/iam_nongc.py
awstools/misc.py
awstools/rds.py
awstools/rdsclient.py
awstools/s3.py
awstools/s3client.py
awstools/secrets.py
goatawstools-2024.7.16.1622.dist-info/METADATA
goatawstools-2024.7.16.1622.dist-info/WHEEL
goatawstools-2024.7.16.1622.dist-info/entry_points.txt
goatawstools-2024.7.16.1622.dist-info/top_level.txt
goatawstools-2024.7.16.1622.dist-info/RECORD
