Metadata-Version: 2.1
Name: goatawstools
Version: 2024.7.16.1622
Summary: AWStools - CLI client for AWS GovCloud
Author-email: Chris Stacks <centerupt@gmail.com>
Classifier: Programming Language :: Python :: 3
Classifier: Operating System :: OS Independent
Requires-Python: >=3.7
Requires-Dist: boto3
Requires-Dist: botocore >=1.31.00
Requires-Dist: click >=8.0.4
Requires-Dist: requests-ntlm
Requires-Dist: aws2
